.gitignore
README.md
setup.py
johndeere/__init__.py
johndeere/client.py
johndeere/enum.py
johndeere/typing.py
johndeere.egg-info/PKG-INFO
johndeere.egg-info/SOURCES.txt
johndeere.egg-info/dependency_links.txt
johndeere.egg-info/requires.txt
johndeere.egg-info/top_level.txt
johndeere/mixins/clients.py
johndeere/mixins/commons.py
johndeere/mixins/farms.py
johndeere/mixins/fields.py
johndeere/mixins/org.py
johndeere/mixins/private.py